dedebug
