Metadata-Version: 2.1
Name: dedebug
Version: 0.7
Summary: Telegram debuger
Home-page: https://github.com/user/markolofsen
Author: Mark
Author-email: markolofsen@gmail.com
License: MIT
Keywords: telegram
Platform: UNKNOWN
Classifier: Development Status :: 3 - Alpha
Classifier: Intended Audience :: Developers
Classifier: Topic :: Software Development :: Build Tools
Classifier: License :: OSI Approved :: MIT License
Classifier: Programming Language :: Python :: 3
Classifier: Programming Language :: Python :: 3.4
Classifier: Programming Language :: Python :: 3.5
Classifier: Programming Language :: Python :: 3.6
